newrelic_cli/__init__.py
newrelic_cli/alerts.py
newrelic_cli/base.py
newrelic_cli/cli.py
newrelic_cli/exceptions.py
newrelic_cli/model.py
newrelic_cli/synthetics.py
newrelic_cli/version.py
newrelic_cli/tests/__init__.py
newrelic_cli/tests/test_alerts.py
newrelic_cli/tests/test_base.py
newrelic_cli/tests/test_synthetics.py
newrelic_cli-1.0.0.dist-info/DESCRIPTION.rst
newrelic_cli-1.0.0.dist-info/METADATA
newrelic_cli-1.0.0.dist-info/RECORD
newrelic_cli-1.0.0.dist-info/WHEEL
newrelic_cli-1.0.0.dist-info/entry_points.txt
newrelic_cli-1.0.0.dist-info/metadata.json
newrelic_cli-1.0.0.dist-info/top_level.txt
