Metadata-Version: 2.0
Name: newrelic-cli
Version: 1.0.0
Summary: Newrelic CLI client
Home-page: https://github.com/NativeInstruments/newrelic-cli
Author: Native Instruments GmbH
Author-email: cloud-devops+github@native-instruments.de
License: MIT
Platform: UNKNOWN
Classifier: License :: OSI Approved :: MIT License
Classifier: Programming Language :: Python :: 2.7
Requires-Dist: jinja2
Requires-Dist: pyyaml
Requires-Dist: requests (>=2.0.0)
